Metadata-Version: 2.1
Name: enigmamachine
Version: 0.0.2
Summary: A basic cryptography libary, simulating the Enigma Machine
Home-page: UNKNOWN
Author: Tomas Rodrigues Alessi
Author-email: tomasalessi@gmail.com
License: MIT
Keywords: cryptography
Platform: UNKNOWN
Classifier: Development Status :: 5 - Production/Stable
Classifier: Intended Audience :: Education
Classifier: Operating System :: Microsoft :: Windows :: Windows 10
Classifier: License :: OSI Approved :: MIT License
Classifier: Programming Language :: Python :: 3
License-File: LICENSE
